ladder/__init__.py
ladder/data/__init__.py
ladder/data/builtin_data.py
ladder/data/real_data.py
ladder/models/__init__.py
ladder/models/basics.py
ladder/models/scvi_variants.py
ladder/scripts/__init__.py
ladder/scripts/metrics.py
ladder/scripts/training.py
ladder/scripts/visuals.py
ladder/scripts/workflows.py
scladder-0.1.0.dist-info/METADATA
scladder-0.1.0.dist-info/WHEEL
scladder-0.1.0.dist-info/licenses/LICENSE
scladder-0.1.0.dist-info/RECORD
